dictjson/__init__.py
dictjson/create.py
dictjson-1.0.2.dist-info/METADATA
dictjson-1.0.2.dist-info/WHEEL
dictjson-1.0.2.dist-info/top_level.txt
dictjson-1.0.2.dist-info/RECORD
