Metadata-Version: 2.1
Name: dictjson
Version: 1.0.2
Summary: Create a dictionary from your json data
Home-page: https://github.com/prakhar33
Author: Prakhar Rai
Author-email: prakhar98.rai@gmail.com
License: MIT
Platform: UNKNOWN
Classifier: License :: OSI Approved :: MIT License
Classifier: Programming Language :: Python :: 3
Classifier: Programming Language :: Python :: 3.7
Classifier: Programming Language :: Python :: 3.8
Requires-Dist: setuptools
Requires-Dist: pathlib
Requires-Dist: simplejson
Requires-Dist: numpy
Requires-Dist: pandas
